get_names_strzelczyk
