Metadata-Version: 1.0
Name: get-names-strzelczyk
Version: 1.0.2
Summary: Super useful library
Home-page: https://github.com
Author: SomeCompany PLC
Author-email: dave@example.com
License: UNKNOWN
Platform: UNKNOWN
